resgen.py
app/__init__.py
app/__main__.py
app/application.py
resgen-1.0.1.dist-info/LICENSE.txt
resgen-1.0.1.dist-info/METADATA
resgen-1.0.1.dist-info/WHEEL
resgen-1.0.1.dist-info/entry_points.txt
resgen-1.0.1.dist-info/top_level.txt
resgen-1.0.1.dist-info/RECORD
